perturbers/__init__.py
perturbers/modeling/__init__.py
perturbers/modeling/models.py
perturbers/modeling/perturber.py
perturbers-0.0.0.dist-info/METADATA
perturbers-0.0.0.dist-info/WHEEL
perturbers-0.0.0.dist-info/top_level.txt
perturbers-0.0.0.dist-info/RECORD
